<resources>
    <!-- Base application theme. -->
    <style name="AppStyles" parent="Theme.AppCompat.Light.DarkActionBar">
        <!-- Customize your theme here. -->
        <item name="android:windowBackground">@color/colorBg</item>
        <item name="android:textColor">@color/colorText</item>
       <item name="colorPrimary">@color/colorPrimary</item>
        <item name="colorPrimaryDark">@color/colorPrimaryDark</item>
        <item name="colorAccent">@color/colorAccent</item>
    </style>
    
    
    <style name="AppThemeButton" parent="@android:style/Widget.Button">
        <item name="android:background">@drawable/hbutton</item>
        <item name="android:buttonStyle">@style/AppThemeButton</item>
        <item name="android:textColor">@color/colorText</item>
    </style>
    
    
    <style name="TextView" >
        <item name="android:textSize">20sp</item>
    </style>
    
    
    <style name="TextView.REZ">
        <item name="fontFamily">sans-serif</item>
        <item name="android:textSize">22sp</item>
        <item name="android:textStyle">bold</item>
        <item name="android:textColor">#3700B3</item>
    </style>
</resources>